closuretree/__init__.py
closuretree/models.py
closuretree/tests.py
closuretree/version.py
django_closuretree-1.2.0.dist-info/DESCRIPTION.rst
django_closuretree-1.2.0.dist-info/METADATA
django_closuretree-1.2.0.dist-info/RECORD
django_closuretree-1.2.0.dist-info/WHEEL
django_closuretree-1.2.0.dist-info/metadata.json
django_closuretree-1.2.0.dist-info/top_level.txt
