Metadata-Version: 2.0
Name: django-closuretree
Version: 1.2.0
Summary: Efficient tree-based datastructure for Django
Home-page: https://github.com/ocadotechnology/django-closuretree/
Author: Mike Bryant
Author-email: mike.bryant@ocado.com
License: UNKNOWN
Platform: UNKNOWN
Classifier: Development Status :: 5 - Production/Stable
Classifier: Framework :: Django
Classifier: Intended Audience :: Developers
Classifier: License :: OSI Approved :: Apache Software License
Classifier: Programming Language :: Python
Classifier: Programming Language :: Python :: 2
Classifier: Programming Language :: Python :: 2.6
Classifier: Programming Language :: Python :: 2.7
Classifier: Programming Language :: Python :: 3
Classifier: Programming Language :: Python :: 3.2
Classifier: Programming Language :: Python :: 3.3
Classifier: Topic :: Software Development :: Libraries :: Python Modules
Requires-Dist: django (<1.12,>=1.4)
Requires-Dist: django-autoconfig
